gen_pdf_prices/__init__.py
gen_pdf_prices/gen_pdf.py
gen_pdf_prices/fonts/a010013l.afm
gen_pdf_prices/fonts/a010013l.pfb
gen_pdf_prices-0.0.5.dist-info/METADATA
gen_pdf_prices-0.0.5.dist-info/RECORD
gen_pdf_prices-0.0.5.dist-info/WHEEL
gen_pdf_prices-0.0.5.dist-info/top_level.txt
