Metadata-Version: 2.1
Name: gen-pdf-prices
Version: 0.0.5
Summary: Generate pdf file with prices
Home-page: UNKNOWN
Author: Druta Ruslan
Author-email: r.druta@dekart.com
License: UNKNOWN
Platform: UNKNOWN
Requires-Dist: reportlab
